{"nodes": [{"group": "0", "id": "ClickMobile Client Template", "hasSizeMember": 1, "nodes": ["<a href='ClickMobile-Client-Template[Copy-(3)-of-Technician-Template---Bundler|Administrative-Settings].html' target='_blank'>ClickMobile Client Template[Copy (3) of Technician Template - Bundler|Administrative Settings]</a><br/>"]}, {"group": "1", "id": "Setting", "hasSizeMember": 1, "nodes": ["<a href='Setting[[Application]|ClickMobile|Dictionaries-Synchronization|].html' target='_blank'>Setting[[Application]|ClickMobile|Dictionaries Synchronization|]</a><br/>"]}], "links": [{"source": "ClickMobile Client Template", "target": "Setting", "value": 1}]}