{"nodes": [{"group": "0", "id": "ButlerService Property", "hasSizeMember": 1, "nodes": ["<a href='ButlerService-Property[ApplicableMobileTemplates].html' target='_blank'>ButlerService Property[ApplicableMobileTemplates]</a><br/>"]}, {"group": "1", "id": "UserSetting", "hasSizeMember": 1, "nodes": ["<a href='UserSetting[Butler-Editor|ClickMobile-Client|Web-Administrative-Settings|].html' target='_blank'>UserSetting[Butler Editor|ClickMobile Client|Web Administrative Settings|]</a><br/>"]}], "links": [{"source": "ButlerService Property", "target": "UserSetting", "value": 1}]}