{"nodes": [{"group": "0", "id": "CancellationReason Property", "hasSizeMember": 2, "nodes": ["<a href='CancellationReason-Property[Key].html' target='_blank'>CancellationReason Property[Key]</a><br/>", "<a href='CancellationReason-Property[Name].html' target='_blank'>CancellationReason Property[Name]</a><br/>"]}, {"group": "1", "id": "Collection", "hasSizeMember": 1, "nodes": ["<a href='Collection[CancellationReason].html' target='_blank'>Collection[CancellationReason]</a><br/>"]}], "links": [{"source": "CancellationReason Property", "target": "Collection", "value": 2}, {"source": "CancellationReason Property", "target": "CancellationReason Property", "value": 1}, {"source": "Collection", "target": "CancellationReason Property", "value": 1}, {"source": "Collection", "target": "Collection", "value": 1}]}