{"nodes": [{"group": "0", "id": "Skill", "hasSizeMember": 1, "nodes": ["<a href='Skill[Max-Repair].html' target='_blank'>Skill[Max Repair]</a><br/>"]}, {"group": "1", "id": "Group", "hasSizeMember": 2, "nodes": ["<a href='Group[_Shift---Consumer-and-Business-Repair].html' target='_blank'>Group[_Shift - Consumer and Business Repair]</a><br/>", "<a href='Group[_Shift---Same-Day-Consumer-and-Business-Repair].html' target='_blank'>Group[_Shift - Same Day Consumer and Business Repair]</a><br/>"]}], "links": [{"source": "Skill", "target": "Group", "value": 2}]}