{"nodes": [{"group": "0", "id": "Collection", "hasSizeMember": 2, "nodes": ["<a href='jsonItem.html?item=d3-2487.json' target='_blank'>Collection[ButlerType]</a><br/>", "<a href='jsonItem.html?item=d3-2482.json' target='_blank'>Collection[ButlerNotification]</a><br/>"]}, {"group": "1", "id": "ButlerNotification Property", "hasSizeMember": 2, "nodes": ["<a href='jsonItem.html?item=d3-1063.json' target='_blank'>ButlerNotification Property[Key]</a><br/>", "<a href='jsonItem.html?item=d3-1060.json' target='_blank'>ButlerNotification Property[ButlerType]</a><br/>"]}, {"group": "2", "id": "Setting", "hasSizeMember": 1, "nodes": ["<a href='jsonItem.html?item=d3-8043.json' target='_blank'>Setting[[Application]|Purge Agent|Purge Agent Settings|Other Collections Definition]</a><br/>"]}, {"group": "3", "id": "ButlerType Property", "hasSizeMember": 1, "nodes": ["<a href='jsonItem.html?item=d3-1163.json' target='_blank'>ButlerType Property[Key]</a><br/>"]}, {"group": "4", "id": "ButlerNotification Index", "hasSizeMember": 1, "nodes": ["<a href='jsonItem.html?item=d3-1058.json' target='_blank'>ButlerNotification Index[Key]</a><br/>"]}, {"group": "5", "id": "ButlerType Index", "hasSizeMember": 1, "nodes": ["<a href='jsonItem.html?item=d3-1161.json' target='_blank'>ButlerType Index[Key]</a><br/>"]}], "links": [{"source": "ButlerNotification Property", "target": "ButlerNotification Index", "value": 1}, {"source": "ButlerNotification Property", "target": "Collection", "value": 1}, {"source": "ButlerType Property", "target": "ButlerType Index", "value": 1}, {"source": "ButlerType Property", "target": "Collection", "value": 1}, {"source": "Collection", "target": "ButlerNotification Property", "value": 2}, {"source": "Collection", "target": "Collection", "value": 3}, {"source": "Collection", "target": "Setting", "value": 1}, {"source": "Collection", "target": "ButlerType Property", "value": 1}]}