{"nodes": [{"group": "0", "id": "DurationRule Index", "hasSizeMember": 1, "nodes": ["<a href='jsonItem.html?item=d3-3386.json' target='_blank'>DurationRule Index[Key]</a><br/>"]}, {"group": "1", "id": "Collection", "hasSizeMember": 1, "nodes": ["<a href='jsonItem.html?item=d3-2546.json' target='_blank'>Collection[DurationRule]</a><br/>"]}, {"group": "2", "id": "DurationRule Property", "hasSizeMember": 2, "nodes": ["<a href='jsonItem.html?item=d3-3390.json' target='_blank'>DurationRule Property[Key]</a><br/>", "<a href='jsonItem.html?item=d3-3391.json' target='_blank'>DurationRule Property[Name]</a><br/>"]}], "links": [{"source": "Collection", "target": "Collection", "value": 1}, {"source": "Collection", "target": "DurationRule Property", "value": 1}, {"source": "DurationRule Property", "target": "Collection", "value": 2}, {"source": "DurationRule Property", "target": "DurationRule Index", "value": 1}, {"source": "DurationRule Property", "target": "DurationRule Property", "value": 1}]}