{"nodes": [{"group": "0", "id": "IncompletionReason", "hasSizeMember": 1, "nodes": ["<a href='jsonItem.html?item=d3-4445.json' target='_blank'>IncompletionReason[PO - All Other Company Reasons]</a><br/>"]}, {"group": "1", "id": "Group", "hasSizeMember": 1, "nodes": ["<a href='jsonItem.html?item=d3-4317.json' target='_blank'>Group[PreventDuplicateMTs]</a><br/>"]}, {"group": "2", "id": "Setting", "hasSizeMember": 1, "nodes": ["<a href='jsonItem.html?item=d3-7778.json' target='_blank'>Setting[[Application]|Agent|Workflow Agent|PR to PO Incomplete Reason]</a><br/>"]}, {"group": "3", "id": "GenericEventDefinition", "hasSizeMember": 1, "nodes": ["<a href='jsonItem.html?item=d3-4055.json' target='_blank'>GenericEventDefinition[Update Cancelled MTs to 5555]</a><br/>"]}], "links": [{"source": "Group", "target": "GenericEventDefinition", "value": 1}, {"source": "IncompletionReason", "target": "Group", "value": 1}, {"source": "IncompletionReason", "target": "Setting", "value": 1}]}