{"nodes": [{"group": "0", "id": "RosterLogicDomains Index", "hasSizeMember": 1, "nodes": ["<a href='jsonItem.html?item=d3-6561.json' target='_blank'>RosterLogicDomains Index[Key]</a><br/>"]}, {"group": "1", "id": "Collection", "hasSizeMember": 1, "nodes": ["<a href='jsonItem.html?item=d3-2693.json' target='_blank'>Collection[RosterLogicDomains]</a><br/>"]}, {"group": "2", "id": "RosterLogicDomains Property", "hasSizeMember": 2, "nodes": ["<a href='jsonItem.html?item=d3-6564.json' target='_blank'>RosterLogicDomains Property[Key]</a><br/>", "<a href='jsonItem.html?item=d3-6571.json' target='_blank'>RosterLogicDomains Property[SubCategory]</a><br/>"]}], "links": [{"source": "Collection", "target": "Collection", "value": 1}, {"source": "Collection", "target": "RosterLogicDomains Property", "value": 1}, {"source": "RosterLogicDomains Property", "target": "Collection", "value": 2}, {"source": "RosterLogicDomains Property", "target": "RosterLogicDomains Index", "value": 1}, {"source": "RosterLogicDomains Property", "target": "RosterLogicDomains Property", "value": 1}]}