{"nodes": [{"group": "0", "id": "BundlerPolicy Index", "hasSizeMember": 1, "nodes": ["<a href='jsonItem.html?item=d3-894.json' target='_blank'>BundlerPolicy Index[Key]</a><br/>"]}, {"group": "1", "id": "Collection", "hasSizeMember": 1, "nodes": ["<a href='jsonItem.html?item=d3-2474.json' target='_blank'>Collection[BundlerPolicy]</a><br/>"]}, {"group": "2", "id": "BundlerPolicy Property", "hasSizeMember": 2, "nodes": ["<a href='jsonItem.html?item=d3-897.json' target='_blank'>BundlerPolicy Property[Key]</a><br/>", "<a href='jsonItem.html?item=d3-898.json' target='_blank'>BundlerPolicy Property[Name]</a><br/>"]}], "links": [{"source": "BundlerPolicy Property", "target": "BundlerPolicy Index", "value": 1}, {"source": "BundlerPolicy Property", "target": "Collection", "value": 2}, {"source": "BundlerPolicy Property", "target": "BundlerPolicy Property", "value": 1}, {"source": "Collection", "target": "BundlerPolicy Property", "value": 1}, {"source": "Collection", "target": "Collection", "value": 1}]}