{"nodes": [{"group": "0", "id": "AuditABCapDynamic Property", "hasSizeMember": 2, "nodes": ["<a href='jsonItem.html?item=d3-551.json' target='_blank'>AuditABCapDynamic Property[Key]</a><br/>", "<a href='jsonItem.html?item=d3-552.json' target='_blank'>AuditABCapDynamic Property[Name]</a><br/>"]}, {"group": "1", "id": "Collection", "hasSizeMember": 1, "nodes": ["<a href='jsonItem.html?item=d3-2460.json' target='_blank'>Collection[AuditABCapDynamic]</a><br/>"]}], "links": [{"source": "AuditABCapDynamic Property", "target": "Collection", "value": 2}, {"source": "AuditABCapDynamic Property", "target": "AuditABCapDynamic Property", "value": 1}, {"source": "Collection", "target": "AuditABCapDynamic Property", "value": 1}, {"source": "Collection", "target": "Collection", "value": 1}]}