{"itemId": "Collection[OperationalPositionType]", "identities": [{"id": "Collection[OperationalPositionType]", "type": "Collection", "fields": {"IdName": "OperationalPositionType"}}], "containtedItems": [{"id": "OperationalPositionType Index[Key]", "xpath": "Indexes/Index[1]"}, {"id": "OperationalPositionType Index[Name]", "xpath": "Indexes/Index[2]"}, {"id": "OperationalPositionType Property[Description]", "xpath": "Attributes/Attribute[4]"}, {"id": "OperationalPositionType Property[Key]", "xpath": "Attributes/Attribute[1]"}, {"id": "OperationalPositionType Property[Name]", "xpath": "Attributes/Attribute[3]"}, {"id": "OperationalPositionType Property[RequiredSkills]", "xpath": "Attributes/Attribute[5]"}, {"id": "OperationalPositionType Property[Revision]", "xpath": "Attributes/Attribute[2]"}, {"id": "W6OPERATIONAL_POS_TYPES_SKILLS Property[SkillKey]", "xpath": "Attributes/Attribute[5]/AttributeCollection/Attributes/Attribute[1]"}, {"id": "W6OPERATIONAL_POS_TYPES_SKILLS Property[SkillLevel]", "xpath": "Attributes/Attribute[5]/AttributeCollection/Attributes/Attribute[2]"}], "dependencies": ["Collection[OperationalPositionType]", "Collection[Skill]", "OperationalPositionType Property[Key]", "OperationalPositionType Property[Name]", "Skill Property[Name]"]}