{"itemId": "Objective[_Eval - Number of Assignments for Sev 5]", "identities": [{"id": "Objective[_Eval - Number of Assignments for Sev 5]", "type": "Objective", "fields": {"Name": "_Eval - Number of Assignments for Sev 5", "ProgID": "W6Objectives.W6PropBasedRevenueBVF, W6Objectives"}}, {"id": "WorkRevenueByPropertyBVF[_Eval - Number of Assignments for Sev 5]", "type": "WorkRevenueByPropertyBVF", "fields": {"Name": "_Eval - Number of Assignments for Sev 5"}}], "dependencies": ["Collection[Task]", "Task Property[Severity]"]}