{"nodes": [{"group": "0", "id": "PredictiveTaskDuration Property", "hasSizeMember": 1, "nodes": ["<a href='PredictiveTaskDuration-Property[Key].html' target='_blank'>PredictiveTaskDuration Property[Key]</a><br/>"]}, {"group": "1", "id": "Collection", "hasSizeMember": 1, "nodes": ["<a href='Collection[PredictiveTaskDuration].html' target='_blank'>Collection[PredictiveTaskDuration]</a><br/>"]}, {"group": "2", "id": "PredictiveTaskDuration Index", "hasSizeMember": 1, "nodes": ["<a href='PredictiveTaskDuration-Index[Key].html' target='_blank'>PredictiveTaskDuration Index[Key]</a><br/>"]}], "links": [{"source": "Collection", "target": "Collection", "value": 1}, {"source": "Collection", "target": "PredictiveTaskDuration Property", "value": 1}, {"source": "PredictiveTaskDuration Property", "target": "Collection", "value": 1}, {"source": "PredictiveTaskDuration Property", "target": "PredictiveTaskDuration Index", "value": 1}]}