{"nodes": [{"group": "0", "id": "RosterNARule Property", "hasSizeMember": 1, "nodes": ["<a href='RosterNARule-Property[Key].html' target='_blank'>RosterNARule Property[Key]</a><br/>"]}, {"group": "1", "id": "Collection", "hasSizeMember": 1, "nodes": ["<a href='Collection[RosterNARule].html' target='_blank'>Collection[RosterNARule]</a><br/>"]}, {"group": "2", "id": "RosterNARule Index", "hasSizeMember": 1, "nodes": ["<a href='RosterNARule-Index[Key].html' target='_blank'>RosterNARule Index[Key]</a><br/>"]}], "links": [{"source": "Collection", "target": "Collection", "value": 1}, {"source": "Collection", "target": "RosterNARule Property", "value": 1}, {"source": "RosterNARule Property", "target": "Collection", "value": 1}, {"source": "RosterNARule Property", "target": "RosterNARule Index", "value": 1}]}