{"nodes": [{"group": "0", "id": "RosterDemandPattern Property", "hasSizeMember": 2, "nodes": ["<a href='RosterDemandPattern-Property[Name].html' target='_blank'>RosterDemandPattern Property[Name]</a><br/>", "<a href='RosterDemandPattern-Property[Key].html' target='_blank'>RosterDemandPattern Property[Key]</a><br/>"]}, {"group": "1", "id": "Collection", "hasSizeMember": 1, "nodes": ["<a href='Collection[RosterDemandPattern].html' target='_blank'>Collection[RosterDemandPattern]</a><br/>"]}, {"group": "2", "id": "Setting", "hasSizeMember": 1, "nodes": ["<a href='Setting[[Application]|ObjectReference|ObjectReference|].html' target='_blank'>Setting[[Application]|ObjectReference|ObjectReference|]</a><br/>"]}, {"group": "3", "id": "RosterDemandPattern Index", "hasSizeMember": 1, "nodes": ["<a href='RosterDemandPattern-Index[Key].html' target='_blank'>RosterDemandPattern Index[Key]</a><br/>"]}], "links": [{"source": "Collection", "target": "Collection", "value": 1}, {"source": "Collection", "target": "RosterDemandPattern Property", "value": 1}, {"source": "RosterDemandPattern Property", "target": "Collection", "value": 2}, {"source": "RosterDemandPattern Property", "target": "RosterDemandPattern Index", "value": 1}, {"source": "RosterDemandPattern Property", "target": "Setting", "value": 1}, {"source": "RosterDemandPattern Property", "target": "RosterDemandPattern Property", "value": 1}]}