{"nodes": [{"group": "0", "id": "BookingArea", "hasSizeMember": 1, "nodes": ["<a href='BookingArea[NORTHBAT].html' target='_blank'>BookingArea[NORTHBAT]</a><br/>"]}, {"group": "1", "id": "Route", "hasSizeMember": 12, "nodes": ["<a href='Route[Unity].html' target='_blank'>Route[Unity]</a><br/>", "<a href='Route[Lloydminster].html' target='_blank'>Route[Lloydminster]</a><br/>", "<a href='Route[Lloydminster-City].html' target='_blank'>Route[Lloydminster City]</a><br/>", "<a href='Route[Kerrobert].html' target='_blank'>Route[Kerrobert]</a><br/>", "<a href='Route[Buffalo-Narrows].html' target='_blank'>Route[Buffalo Narrows]</a><br/>", "<a href='Route[Town-of-Kindersley].html' target='_blank'>Route[Town of Kindersley]</a><br/>", "<a href='Route[Town-of-Meadow-Lake].html' target='_blank'>Route[Town of Meadow Lake]</a><br/>", "<a href='Route[Meadow-Lake].html' target='_blank'>Route[Meadow Lake]</a><br/>", "<a href='Route[Kindersley].html' target='_blank'>Route[Kindersley]</a><br/>", "<a href='Route[Pinehouse].html' target='_blank'>Route[Pinehouse]</a><br/>", "<a href='Route[North-Battleford-City].html' target='_blank'>Route[North Battleford City]</a><br/>", "<a href='Route[North-Battleford].html' target='_blank'>Route[North Battleford]</a><br/>"]}], "links": [{"source": "BookingArea", "target": "Route", "value": 12}]}