{"nodes": [{"group": "0", "id": "ServiceNotification Property", "hasSizeMember": 1, "nodes": ["<a href='ServiceNotification-Property[ServiceNotificationStatus].html' target='_blank'>ServiceNotification Property[ServiceNotificationStatus]</a><br/>"]}, {"group": "1", "id": "Collection", "hasSizeMember": 1, "nodes": ["<a href='Collection[ServiceNotificationStatus].html' target='_blank'>Collection[ServiceNotificationStatus]</a><br/>"]}, {"group": "2", "id": "ServiceNotificationStatus Property", "hasSizeMember": 2, "nodes": ["<a href='ServiceNotificationStatus-Property[Key].html' target='_blank'>ServiceNotificationStatus Property[Key]</a><br/>", "<a href='ServiceNotificationStatus-Property[Name].html' target='_blank'>ServiceNotificationStatus Property[Name]</a><br/>"]}], "links": [{"source": "Collection", "target": "Collection", "value": 1}, {"source": "Collection", "target": "ServiceNotification Property", "value": 1}, {"source": "Collection", "target": "ServiceNotificationStatus Property", "value": 1}, {"source": "ServiceNotificationStatus Property", "target": "Collection", "value": 2}, {"source": "ServiceNotificationStatus Property", "target": "ServiceNotification Property", "value": 1}, {"source": "ServiceNotificationStatus Property", "target": "ServiceNotificationStatus Property", "value": 1}]}