{"nodes": [{"group": "0", "id": "Task Property", "hasSizeMember": 1, "nodes": ["<a href='Task-Property[ProblemKeywords].html' target='_blank'>Task Property[ProblemKeywords]</a><br/>"]}, {"group": "1", "id": "ProblemKeyword Property", "hasSizeMember": 2, "nodes": ["<a href='ProblemKeyword-Property[Key].html' target='_blank'>ProblemKeyword Property[Key]</a><br/>", "<a href='ProblemKeyword-Property[Name].html' target='_blank'>ProblemKeyword Property[Name]</a><br/>"]}, {"group": "2", "id": "Collection", "hasSizeMember": 1, "nodes": ["<a href='Collection[ProblemKeyword].html' target='_blank'>Collection[ProblemKeyword]</a><br/>"]}], "links": [{"source": "Collection", "target": "Collection", "value": 1}, {"source": "Collection", "target": "ProblemKeyword Property", "value": 1}, {"source": "Collection", "target": "Task Property", "value": 1}, {"source": "ProblemKeyword Property", "target": "Collection", "value": 2}, {"source": "ProblemKeyword Property", "target": "ProblemKeyword Property", "value": 1}, {"source": "ProblemKeyword Property", "target": "Task Property", "value": 1}]}