{"nodes": [{"group": 0, "id": "X365", "hasSizeMember": 1, "nodes": ["<a href='jsonItem.html?item=d3-X365.json' target='_blank'>AppProductType Property[Key]</a><br/>"]}, {"group": 1, "id": "Setting", "hasSizeMember": 1, "nodes": ["<a href=\"jsonItem.html?item=d3-X10385.json\" target=\"_blank\">['X10385', 'Setting[[Application]|ObjectReference|ObjectReference|]']</a><br/>"]}, {"group": 2, "id": "App Property", "hasSizeMember": 4, "nodes": ["<a href=\"jsonItem.html?item=d3-X277.json\" target=\"_blank\">['X277', 'App Property[Prerequisites]']</a><br/>", "<a href=\"jsonItem.html?item=d3-X271.json\" target=\"_blank\">['X271', 'App Property[Key]']</a><br/>", "<a href=\"jsonItem.html?item=d3-X278.json\" target=\"_blank\">['X278', 'App Property[Product]']</a><br/>", "<a href=\"jsonItem.html?item=d3-X283.json\" target=\"_blank\">['X283', 'App Property[SupportedProducts]']</a><br/>"]}, {"group": 3, "id": "StandardSetting", "hasSizeMember": 1, "nodes": ["<a href=\"jsonItem.html?item=d3-X10385.json\" target=\"_blank\">['X10385', 'StandardSetting[[Application]|ObjectReference|ObjectReference|]']</a><br/>"]}, {"group": 4, "id": "App Index", "hasSizeMember": 2, "nodes": ["<a href=\"jsonItem.html?item=d3-X262.json\" target=\"_blank\">['X262', 'App Index[Name,MajorVersion,MinorVersion,Product]']</a><br/>", "<a href=\"jsonItem.html?item=d3-X261.json\" target=\"_blank\">['X261', 'App Index[Key]']</a><br/>"]}, {"group": 5, "id": "Collection", "hasSizeMember": 2, "nodes": ["<a href=\"jsonItem.html?item=d3-X2454.json\" target=\"_blank\">['X2454', 'Collection[AppProductType]']</a><br/>", "<a href=\"jsonItem.html?item=d3-X2451.json\" target=\"_blank\">['X2451', 'Collection[App]']</a><br/>"]}, {"group": 6, "id": "W6APP_SUPPORTEDPRODUCTS Property", "hasSizeMember": 1, "nodes": ["<a href=\"jsonItem.html?item=d3-X9163.json\" target=\"_blank\">['X9163', 'W6APP_SUPPORTEDPRODUCTS Property[Product]']</a><br/>"]}, {"group": 7, "id": "AppProductType Index", "hasSizeMember": 1, "nodes": ["<a href=\"jsonItem.html?item=d3-X363.json\" target=\"_blank\">['X363', 'AppProductType Index[Key]']</a><br/>"]}, {"group": 8, "id": "W6APP_PREREQUISITES Property", "hasSizeMember": 1, "nodes": ["<a href=\"jsonItem.html?item=d3-X9162.json\" target=\"_blank\">['X9162', 'W6APP_PREREQUISITES Property[RequiredApp]']</a><br/>"]}], "links": [{"source": "Setting", "target": "App Property", "value": 1}, {"source": "App Property", "target": "Collection", "value": 1}, {"source": "StandardSetting", "target": "App Property", "value": 1}, {"source": "App Index", "target": "App Property", "value": 1}, {"source": "Collection", "target": "X365", "value": 1}, {"source": "Collection", "target": "Collection", "value": 1}, {"source": "Collection", "target": "App Property", "value": 1}, {"source": "X365", "target": "Collection", "value": 1}, {"source": "W6APP_SUPPORTEDPRODUCTS Property", "target": "Collection", "value": 1}, {"source": "AppProductType Index", "target": "X365", "value": 1}, {"source": "W6APP_PREREQUISITES Property", "target": "Collection", "value": 1}]}