{"nodes": [{"group": 0, "id": "X2675", "hasSizeMember": 1, "nodes": ["<a href='jsonItem.html?item=d3-X2675.json' target='_blank'>Collection[ReserveCapacityInApptBookingRule]</a><br/>"]}, {"group": 1, "id": "AppointmentBookingCapacitySettings Property", "hasSizeMember": 2, "nodes": ["<a href=\"jsonItem.html?item=d3-X296.json\" target=\"_blank\">['X296', 'AppointmentBookingCapacitySettings Property[Key]']</a><br/>", "<a href=\"jsonItem.html?item=d3-X299.json\" target=\"_blank\">['X299', 'AppointmentBookingCapacitySettings Property[ReserveCapcityInAppBookingRule]']</a><br/>"]}, {"group": 2, "id": "Collection", "hasSizeMember": 1, "nodes": ["<a href=\"jsonItem.html?item=d3-X2452.json\" target=\"_blank\">['X2452', 'Collection[AppointmentBookingCapacitySettings]']</a><br/>"]}, {"group": 3, "id": "ReserveCapacityInApptBookingRule Property", "hasSizeMember": 1, "nodes": ["<a href=\"jsonItem.html?item=d3-X6067.json\" target=\"_blank\">['X6067', 'ReserveCapacityInApptBookingRule Property[Key]']</a><br/>"]}, {"group": 4, "id": "AppointmentBookingCapacitySettings Index", "hasSizeMember": 1, "nodes": ["<a href=\"jsonItem.html?item=d3-X291.json\" target=\"_blank\">['X291', 'AppointmentBookingCapacitySettings Index[Key]']</a><br/>"]}, {"group": 5, "id": "ReserveCapacityInApptBookingRule Index", "hasSizeMember": 1, "nodes": ["<a href=\"jsonItem.html?item=d3-X6054.json\" target=\"_blank\">['X6054', 'ReserveCapacityInApptBookingRule Index[Key]']</a><br/>"]}], "links": [{"source": "AppointmentBookingCapacitySettings Property", "target": "Collection", "value": 1}, {"source": "AppointmentBookingCapacitySettings Property", "target": "X2675", "value": 1}, {"source": "Collection", "target": "AppointmentBookingCapacitySettings Property", "value": 1}, {"source": "Collection", "target": "Collection", "value": 1}, {"source": "Collection", "target": "X2675", "value": 1}, {"source": "ReserveCapacityInApptBookingRule Property", "target": "X2675", "value": 1}, {"source": "X2675", "target": "Collection", "value": 1}, {"source": "X2675", "target": "ReserveCapacityInApptBookingRule Property", "value": 1}, {"source": "AppointmentBookingCapacitySettings Index", "target": "AppointmentBookingCapacitySettings Property", "value": 1}, {"source": "ReserveCapacityInApptBookingRule Index", "target": "ReserveCapacityInApptBookingRule Property", "value": 1}]}